linkgen/__init__.py
linkgen/__main__.py
linkgen/linkgen.py
linkgen/utils.py
linkgen/.pytest_cache/.gitignore
linkgen/.pytest_cache/CACHEDIR.TAG
linkgen/.pytest_cache/README.md
linkgen/.pytest_cache/v/cache/lastfailed
linkgen/.pytest_cache/v/cache/nodeids
linkgen/.pytest_cache/v/cache/stepwise
linkgen/tests/__init__.py
linkgen/tests/test_linkgen.py
linkgen-0.1.0.dist-info/entry_points.txt
linkgen-0.1.0.dist-info/LICENSE
linkgen-0.1.0.dist-info/WHEEL
linkgen-0.1.0.dist-info/METADATA
linkgen-0.1.0.dist-info/RECORD
