Metadata-Version: 2.1
Name: linkgen
Version: 0.1.0
Summary: Static site generator for Linktree-like webpages
Author-email: Anna <cyber@sysrq.in>
Classifier: Environment :: Console
Classifier: License :: Public Domain
Classifier: Programming Language :: Python :: 3
Classifier: Topic :: Internet :: WWW/HTTP
Requires-Dist: tomli; python_version < '3.11'
Project-URL: Home, https://git.sysrq.in/linkgen-web/about
